translatepy/LICENSE
translatepy/__init__.py
translatepy/__main__.py
translatepy/exceptions.py
translatepy/language.py
translatepy/models.py
translatepy/translate.py
translatepy/translators/__init__.py
translatepy/translators/base.py
translatepy/translators/bing.py
translatepy/translators/deepl.py
translatepy/translators/google.py
translatepy/translators/libre.py
translatepy/translators/mymemory.py
translatepy/translators/reverso.py
translatepy/translators/translatecom.py
translatepy/translators/yandex.py
translatepy/utils/__init__.py
translatepy/utils/_language_data.py
translatepy/utils/annotations.py
translatepy/utils/gtoken.py
translatepy/utils/lru_cacher.py
translatepy/utils/queue.py
translatepy/utils/request.py
translatepy/utils/sanitize.py
translatepy/utils/similarity.py
translatepy/utils/utils.py
translatepy-2.2.dist-info/LICENSE
translatepy-2.2.dist-info/METADATA
translatepy-2.2.dist-info/WHEEL
translatepy-2.2.dist-info/entry_points.txt
translatepy-2.2.dist-info/top_level.txt
translatepy-2.2.dist-info/RECORD
