Metadata-Version: 2.1
Name: translatepy
Version: 2.2
Summary: Translate, transliterate, get the language of texts in no time with the help of multiple APIs!
Home-page: https://github.com/Animenosekai/translate
Author: Anime no Sekai
Author-email: niichannomail@gmail.com
License: GNU General Public License v3 (GPLv3)
Download-URL: https://github.com/Animenosekai/translate/archive/v2.2.tar.gz
Keywords: python,translate,translation,google-translate,yandex-translate,bing-translate,reverso,transliteration,detect-language,text-to-speech,deepl,language
Platform: UNKNOWN
Classifier: Development Status :: 5 - Production/Stable
Classifier: License :: OSI Approved :: GNU General Public License v3 (GPLv3)
Classifier: Programming Language :: Python :: 3
Classifier: Programming Language :: Python :: 3.2
Classifier: Programming Language :: Python :: 3.3
Classifier: Programming Language :: Python :: 3.4
Classifier: Programming Language :: Python :: 3.5
Classifier: Programming Language :: Python :: 3.6
Classifier: Programming Language :: Python :: 3.7
Classifier: Programming Language :: Python :: 3.8
Classifier: Programming Language :: Python :: 3.9
Requires-Python: >=3.2, <4
License-File: LICENSE
Requires-Dist: requests
Requires-Dist: beautifulsoup4
Requires-Dist: pyuseragents
Requires-Dist: inquirer
Requires-Dist: typing ; python_version < "3.5"
